chatgpttwilio/__init__.py
thiruchatgpt-0.0.2.dist-info/METADATA
thiruchatgpt-0.0.2.dist-info/WHEEL
thiruchatgpt-0.0.2.dist-info/top_level.txt
thiruchatgpt-0.0.2.dist-info/RECORD
