Metadata-Version: 2.1
Name: thiruchatgpt
Version: 0.0.2
Summary: ChatGPT In Whatsapp Using Twilio
Home-page: UNKNOWN
Author: Thirumalai K G
License: UNKNOWN
Keywords: python,openai,chatgpt,twilio,whatsapp,chatting
Platform: UNKNOWN
Classifier: Development Status :: 1 - Planning
Classifier: Intended Audience :: Developers
Classifier: Programming Language :: Python :: 3
Classifier: Operating System :: Unix
Classifier: Operating System :: MacOS :: MacOS X
Classifier: Operating System :: Microsoft :: Windows
Requires-Dist: flask
Requires-Dist: twilio
Requires-Dist: openai
